README.md
setup.cfg
setup.py
litecoder/__init__.py
litecoder/db.py
litecoder/usa.py
litecoder/utils.py
litecoder.egg-info/PKG-INFO
litecoder.egg-info/SOURCES.txt
litecoder.egg-info/dependency_links.txt
litecoder.egg-info/requires.txt
litecoder.egg-info/top_level.txt
litecoder/models/__init__.py
litecoder/models/base.py
litecoder/models/wof_county.py
litecoder/models/wof_locality.py
litecoder/models/wof_region.py
litecoder/sources/__init__.py
litecoder/sources/wof.py
tests/__init__.py
tests/utils.py
tests/prod_db/__init__.py
tests/prod_db/conftest.py
tests/prod_db/test_bare_name_blocklist.py
tests/prod_db/test_us_city_index.py
tests/prod_db/test_us_state_index.py
tests/test_db/__init__.py
tests/test_db/conftest.py
tests/test_db/test_ingest_county.py
tests/test_db/test_ingest_locality.py
tests/test_db/test_ingest_region.py
tests/test_db/test_keyify.py